drishti/datasets/__init__.py
drishti/datasets/bbox.py
drishti/datasets/image.py
drishti/datasets/object_dataset.py
drishti/datasets/pascal/__init__.py
drishti/datasets/pascal/voc.py
drishti-0.1.2.dist-info/METADATA
drishti-0.1.2.dist-info/RECORD
drishti-0.1.2.dist-info/WHEEL
drishti-0.1.2.dist-info/top_level.txt
