Metadata-Version: 2.1
Name: drishti
Version: 0.1.2
Summary: module to simplify computer vision tasks
Home-page: https://gitlab.com/abhishek.ambastha/computer-vision/tree/master/drishti
Author: Abhishek Ambastha
Author-email: ambastha.abhishek@gmail.com
License: MIT
Platform: UNKNOWN
Requires-Dist: numpy
Requires-Dist: matplotlib
Requires-Dist: untangle
Requires-Dist: tqdm
Requires-Dist: opencv-python
